qre/__init__.py
qre/registered_types.py
qre-22.10.2.dist-info/LICENSE
qre-22.10.2.dist-info/WHEEL
qre-22.10.2.dist-info/METADATA
qre-22.10.2.dist-info/RECORD
