Metadata-Version: 2.1
Name: qre
Version: 22.10.2
Summary: Like re, but cuter.
Home-page: https://github.com/mikaelho/qre
License: MIT
Keywords: string,pattern,matching,regular,expression,regex
Author: Mikael Honkala
Author-email: mikael.honkala@gmail.com
Requires-Python: >=3.7,<4.0
Classifier: Development Status :: 5 - Production/Stable
Classifier: License :: OSI Approved :: MIT License
Classifier: Operating System :: OS Independent
Classifier: Programming Language :: Python :: 3
Classifier: Programming Language :: Python :: 3.10
Classifier: Programming Language :: Python :: 3.7
Classifier: Programming Language :: Python :: 3.8
Classifier: Programming Language :: Python :: 3.9
Classifier: Topic :: Software Development :: Libraries
Classifier: Topic :: Text Processing
Classifier: Topic :: Utilities
Project-URL: Repository, https://github.com/mikaelho/qre
